{
  "install_requires": [
    "decorator<5",
    "future",
    "nose",
    "numpy",
    "pyparsing<3",
    "six"
  ],
  "tests_require": [],
  "srcdir": "src",
  "package_name": "PyContracts3",
  "entry_points": {
    "console_scripts": []
  },
  "zip_safe": true,
  "include_package_data": true,
  "modules": [
    "contracts",
    "contracts.library",
    "contracts.testing",
    "contracts.testing.library",
    "contracts.useful_contracts"
  ],
  "version": "7.1.2106301835",
  "author": "Andrea Censi",
  "author_email": "andrea@zupermind.com",
  "url": "https://github.com/AndreaCensi/contracts"
}